fulljson/__init__.py
fulljson/collections.py
fulljson/decoder.py
fulljson/encoder.py
fulljson/errors.py
fulljson/util.py
fulljson-0.0.53.dist-info/LICENSE
fulljson-0.0.53.dist-info/METADATA
fulljson-0.0.53.dist-info/WHEEL
fulljson-0.0.53.dist-info/top_level.txt
fulljson-0.0.53.dist-info/RECORD
