Metadata-Version: 2.1
Name: fulljson
Version: 0.0.53
Summary: simple json conversion implements using stack structure and recursive method
Home-page: https://github.com/15045120/FullJSON
Author: 15045120
Author-email: 1337078409@qq.com
License: UNKNOWN
Platform: UNKNOWN
Classifier: Programming Language :: Python :: 3
Classifier: License :: OSI Approved :: MIT License
Classifier: Operating System :: OS Independent
Requires-Python: >=3
